musurgia/__init__.py
musurgia/arithmeticprogression.py
musurgia/chordfactory/chordfactory.py
musurgia/chordfactory/midigenerators.py
musurgia/magicrandom.py
musurgia/matrix/__init__.py
musurgia/matrix/matrix.py
musurgia/musurgia_exceptions.py
musurgia/musurgia_types.py
musurgia/pdf/__init__.py
musurgia/pdf/drawobject.py
musurgia/pdf/font.py
musurgia/pdf/labeled.py
musurgia/pdf/line.py
musurgia/pdf/margined.py
musurgia/pdf/pdf.py
musurgia/pdf/pdf_tools.py
musurgia/pdf/pdfunit.py
musurgia/pdf/positioned.py
musurgia/pdf/rowcolumn.py
musurgia/pdf/ruler.py
musurgia/pdf/text.py
musurgia/permutation/__init__.py
musurgia/permutation/limited_permutation.py
musurgia/permutation/matrix.md
musurgia/permutation/permutation.py
musurgia/py.typed
musurgia/quantize.py
musurgia/tests/__init__.py
musurgia/tests/chord_factory/test_chordfactory.py
musurgia/tests/chord_factory/test_midigenerator.py
musurgia/tests/debug/test_debug.py
musurgia/tests/pdf/__init__.py
musurgia/tests/pdf/absolute_y/__init__.py
musurgia/tests/pdf/absolute_y/test_aboslute_y.py
musurgia/tests/pdf/clip/__init__.py
musurgia/tests/pdf/clip/test_clip.py
musurgia/tests/pdf/clip/test_clip_clipped_draw.pdf
musurgia/tests/pdf/clip/test_clip_clipped_draw_expected.pdf
musurgia/tests/pdf/clip/test_clip_column_line_break.pdf
musurgia/tests/pdf/clip/test_clip_column_line_break_expected.pdf
musurgia/tests/pdf/clip/test_clip_column_page_break.pdf
musurgia/tests/pdf/clip/test_clip_column_page_break_expected.pdf
musurgia/tests/pdf/clip/test_clip_line.pdf
musurgia/tests/pdf/clip/test_clip_line_break.pdf
musurgia/tests/pdf/clip/test_clip_line_break_expected.pdf
musurgia/tests/pdf/clip/test_clip_line_expected.pdf
musurgia/tests/pdf/clip/test_clip_with_clipping_area.pdf
musurgia/tests/pdf/clip/test_clip_with_clipping_area_expected.pdf
musurgia/tests/pdf/line/__init__.py
musurgia/tests/pdf/line/horizontal_line_segment/__init__.py
musurgia/tests/pdf/line/horizontal_line_segment/test_horizontal_line_segment.py
musurgia-3.2.0.dist-info/METADATA
musurgia-3.2.0.dist-info/WHEEL
musurgia-3.2.0.dist-info/RECORD
