Metadata-Version: 2.1
Name: musurgia
Version: 3.2.0
Summary: Tools for algorithmic composition.
Home-page: https://github.com/alexgorji/musurgia.git
License: MIT
Author: Alex Gorji
Author-email: aligorji@hotmail.com
Requires-Python: >=3.9,<3.13
Classifier: License :: OSI Approved :: MIT License
Classifier: Operating System :: OS Independent
Classifier: Programming Language :: Python :: 3
Classifier: Programming Language :: Python :: 3.9
Classifier: Programming Language :: Python :: 3.10
Classifier: Programming Language :: Python :: 3.11
Classifier: Programming Language :: Python :: 3.12
Requires-Dist: fpdf2 (>=2.8.2,<3.0.0)
Requires-Dist: matplotlib (>=3.9.0,<4.0.0)
Requires-Dist: musicscore (>=2.4.1,<3.0.0)
Requires-Dist: verysimpletree (>=1.2,<2.0)
Project-URL: Repository, https://github.com/alexgorji/musurgia.git
